{
  "version": "5",
  "dialect": "pg",
  "entries": [
    {
      "idx": 0,
      "version": "5",
      "when": 1706140800000,
      "tag": "0000_broad_baron_zemo",
      "breakpoints": true
    },
    {
      "idx": 1,
      "version": "5",
      "when": 1769312319410,
      "tag": "0001_light_husk",
      "breakpoints": true
    },
    {
      "idx": 2,
      "version": "5",
      "when": 1769312339179,
      "tag": "0002_outstanding_venus",
      "breakpoints": true
    },
    {
      "idx": 3,
      "version": "5",
      "when": 1769312380527,
      "tag": "0003_legal_shooting_star",
      "breakpoints": true
    }
  ]
}