{
  "version": "5",
  "dialect": "pg",
  "entries": [
    {
      "idx": 0,
      "version": "5",
      "when": 1706140800000,
      "tag": "0000_broad_baron_zemo",
      "breakpoints": true
    },
    {
      "idx": 1,
      "version": "5",
      "when": 1769312319410,
      "tag": "0001_light_husk",
      "breakpoints": true
    },
    {
      "idx": 2,
      "version": "5",
      "when": 1769312339179,
      "tag": "0002_outstanding_venus",
      "breakpoints": true
    },
    {
      "idx": 3,
      "version": "5",
      "when": 1769312380527,
      "tag": "0003_legal_shooting_star",
      "breakpoints": true
    },
    {
      "idx": 4,
      "version": "5",
      "when": 1769393565896,
      "tag": "0004_peaceful_korvac",
      "breakpoints": true
    },
    {
      "idx": 5,
      "version": "5",
      "when": 1769395711285,
      "tag": "0005_flowery_king_bedlam",
      "breakpoints": true
    },
    {
      "idx": 6,
      "version": "5",
      "when": 1769399570793,
      "tag": "0006_silent_the_stranger",
      "breakpoints": true
    },
    {
      "idx": 7,
      "version": "5",
      "when": 1769402037814,
      "tag": "0007_daily_ultragirl",
      "breakpoints": true
    }
  ]
}